{
  "lottery_name": "SAMRUDHI",
  "draw_number": "SM-14",
  "draw_date": "2025-08-03",
  "venue": "",
  "prizes": {
    "1st_prize": {
      "amount": 10000000,
      "label": "1st Prize",
      "winners": [
        "MR 677584 (PUNALUR)"
      ]
    },
    "consolation_prize": {
      "amount": 5000,
      "label": "Consolation Prize",
      "winners": [
        "MN 677584",
        "MO 677584",
        "MP 677584",
        "MS 677584",
        "MT 677584",
        "MU 677584",
        "MV 677584",
        "MW 677584",
        "MX 677584",
        "MY 677584",
        "MZ 677584"
      ]
    },
    "2nd_prize": {
      "amount": 3000000,
      "label": "2nd Prize",
      "winners": [
        "MW 770190 (CHITTUR)"
      ]
    },
    "3rd_prize": {
      "amount": 500000,
      "label": "3rd Prize",
      "winners": [
        "MX 600445 (THRISSUR)"
      ]
    },
    "4th_prize": {
      "amount": 5000,
      "label": "4th Prize",
      "winners": [
        "0259",
        "1595",
        "1709",
        "2309",
        "2416",
        "3097",
        "3526",
        "3581",
        "4193",
        "4710",
        "4904",
        "5758",
        "6352",
        "6775",
        "7240",
        "8136",
        "9419",
        "9545",
        "9725",
        "9810"
      ]
    },
    "5th_prize": {
      "amount": 2000,
      "label": "5th Prize",
      "winners": [
        "2142",
        "3582",
        "3969",
        "4461",
        "6678",
        "8117"
      ]
    },
    "6th_prize": {
      "amount": 1000,
      "label": "6th Prize",
      "winners": [
        "0229",
        "0512",
        "0877",
        "1412",
        "1627",
        "1838",
        "1980",
        "2271",
        "2383",
        "2423",
        "2693",
        "3709",
        "3904",
        "3960",
        "4301",
        "5215",
        "5707",
        "5922",
        "6501",
        "6894",
        "7002",
        "7053",
        "7249",
        "7536",
        "7689",
        "7692",
        "8108",
        "8498",
        "9054",
        "9087"
      ]
    },
    "7th_prize": {
      "amount": 500,
      "label": "7th Prize",
      "winners": [
        "0177",
        "0178",
        "0198",
        "0447",
        "0529",
        "0541",
        "0630",
        "0634",
        "0830",
        "0851",
        "0964",
        "1221",
        "1222",
        "1268",
        "1409",
        "1440",
        "1633",
        "1639",
        "1810",
        "1921",
        "2060",
        "2100",
        "2703",
        "2770",
        "3344",
        "3493",
        "3704",
        "3747",
        "3905",
        "4162",
        "4196",
        "4247",
        "4286",
        "4477",
        "4485",
        "4520",
        "4670",
        "4690",
        "4774",
        "4942",
        "4968",
        "5066",
        "5401",
        "5430",
        "5439",
        "5446",
        "5599",
        "5876",
        "5880",
        "6019",
        "6118",
        "6237",
        "6266",
        "6344",
        "6726",
        "6814",
        "6978",
        "7036",
        "7067",
        "7344",
        "7683",
        "7916",
        "8161",
        "8555",
        "8623",
        "9014",
        "9077",
        "9095",
        "9208",
        "9511",
        "9516",
        "9527",
        "9598",
        "9863",
        "9884",
        "9949"
      ]
    },
    "8th_prize": {
      "amount": 200,
      "label": "8th Prize",
      "winners": [
        "0007",
        "0135",
        "0146",
        "0147",
        "0171",
        "0204",
        "0542",
        "0549",
        "0726",
        "0807",
        "0814",
        "0994",
        "1133",
        "1646",
        "1797",
        "1875",
        "1914",
        "1934",
        "2099",
        "2198",
        "2235",
        "2419",
        "2669",
        "2973",
        "3134",
        "3291",
        "3479",
        "3614",
        "3627",
        "3753",
        "3803",
        "4240",
        "4284",
        "4296",
        "4354",
        "4366",
        "4454",
        "4550",
        "4600",
        "4633",
        "4785",
        "4804",
        "4805",
        "4987",
        "5095",
        "5129",
        "5367",
        "5422",
        "5647",
        "5714",
        "5715",
        "5770",
        "6089",
        "6147",
        "6160",
        "6296",
        "6379",
        "6493",
        "6517",
        "6575",
        "6657",
        "6688",
        "6738",
        "7097",
        "7276",
        "7297",
        "7301",
        "7321",
        "7380",
        "7404",
        "7512",
        "7560",
        "7729",
        "7839",
        "7874",
        "7918",
        "7951",
        "8160",
        "8185",
        "8435",
        "8600",
        "8636",
        "8732",
        "8866",
        "8870",
        "8928",
        "8998",
        "9008",
        "9031",
        "9062",
        "9112",
        "9889"
      ]
    },
    "9th_prize": {
      "amount": 100,
      "label": "9th Prize",
      "winners": [
        "0004",
        "0077",
        "0201",
        "0218",
        "0296",
        "0440",
        "0722",
        "0764",
        "0782",
        "0801",
        "0935",
        "1028",
        "1053",
        "1092",
        "1122",
        "1159",
        "1541",
        "1605",
        "1665",
        "1804",
        "1950",
        "1958",
        "1972",
        "2005",
        "2055",
        "2071",
        "2135",
        "2167",
        "2200",
        "2245",
        "2278",
        "2285",
        "2372",
        "2396",
        "2422",
        "2493",
        "2547",
        "2569",
        "2598",
        "2662",
        "2697",
        "2822",
        "2853",
        "2876",
        "2972",
        "3064",
        "3076",
        "3157",
        "3183",
        "3186",
        "3240",
        "3569",
        "3595",
        "3646",
        "3742",
        "3767",
        "3824",
        "3841",
        "3934",
        "4048",
        "4069",
        "4090",
        "4245",
        "4337",
        "4390",
        "4538",
        "4566",
        "4607",
        "4689",
        "4737",
        "4760",
        "4782",
        "4988",
        "5032",
        "5076",
        "5092",
        "5174",
        "5216",
        "5248",
        "5288",
        "5324",
        "5344",
        "5464",
        "5602",
        "5651",
        "5659",
        "5669",
        "5679",
        "5739",
        "5769",
        "5878",
        "5909",
        "5929",
        "5938",
        "5956",
        "6031",
        "6194",
        "6264",
        "6465",
        "6534",
        "6751",
        "6781",
        "6811",
        "6931",
        "6941",
        "6999",
        "7043",
        "7090",
        "7130",
        "7150",
        "7287",
        "7439",
        "7487",
        "7594",
        "7758",
        "7811",
        "7819",
        "7844",
        "7896",
        "7923",
        "7932",
        "8209",
        "8335",
        "8346",
        "8355",
        "8414",
        "8496",
        "8599",
        "8654",
        "8670",
        "8744",
        "8942",
        "8944",
        "8946",
        "8986",
        "9037",
        "9123",
        "9136",
        "9147",
        "9244",
        "9271",
        "9299",
        "9480",
        "9485",
        "9500",
        "9515",
        "9610",
        "9919",
        "9960",
        "9990"
      ]
    }
  },
  "downloadLink": ""
}